{
    "name": "RIJO",
    "first_name": "YONI",
    "job_title": "HelpDesk L2",
    "skills": {
        "Cloud & Identity Management": [
            "Active Directory",
            "Microsoft Azure AD",
            "Intune",
            "Mobile Device Management",
            "Airwatch",
            "Okta",
            "Microsoft Identity Manager"
        ],
        "Device & Application Management": [
            "EDI",
            "SAP",
            "AS400",
            "Microsoft Office 365 Pro Pack",
            "Sharepoint",
            "Sales Force",
            "Lotus Note",
            "ServiceNow",
            "Smart IT",
            "Bomgar",
            "Teamviewer"
        ],
        "Networking & Infrastructure": [
            "Windows Server",
            "DHCP",
            "DNS",
            "CISCO 360"
        ],
        "Software & Operating Systems": [
            "Citrix",
            "IOS",
            "Android",
            "Mac OS",
            "Windows 7",
            "Windows 10",
            "Windows 11",
            "Google Chrome",
            "Internet Explorer",
            "Mozilla Firefox",
            "Safari"
        ]
    },
    "languages": {
        "French": "Native or bilingual proficiency \u2013 C2",
        "English": "Professional working proficiency \u2013 C1",
        "Portuguese": "Professional working proficiency \u2013 C1"
    },
    "experiences": [
        {
            "job_title": "IT Technical Support",
            "company": "COGNIZANT",
            "duration": "07/2023 \u2013 08/2024",
            "description": "- Assisted users on-site or remotely\r\n- Managed IT assets and provided remote control support via Bomgar\r\n- Hands-on experience with Windows 10 and Active Directory\r\n- Managed a complete IT device fleet along with 2 colleagues at level 2 and a level 3 supervisor\r\n- Created IAM and Active Directory profiles via Azure portal\r\n- Utilized VPN pulse secure and ServiceNow ticketing tool",
            "client_references": []
        },
        {
            "job_title": "Content Manager",
            "company": "ACCENTURE",
            "duration": "09/2022 \u2013 06/2023",
            "description": "- Managed content on social networks and ensured compliance with client policies against sensitive, violent, and other prohibited content",
            "client_references": []
        },
        {
            "job_title": "IT Field Agent",
            "company": "CTG",
            "duration": "05/2022-09/2022",
            "description": "- Performed Identity and Access Management for the European Investment Bank\r\n- Created profiles, distribution lists, shared mailboxes, and assigned access according to ITSM protocols\r\n- Managed Smart IT ticketing tool and handled external email legitimacy",
            "client_references": []
        },
        {
            "job_title": "IT Field Agent",
            "company": "GLOBALBLUE (GITEC)",
            "duration": "03/2021-05/2022",
            "description": "- Assisted users via remote support tools and administrative elevations\r\n- Provided client hardware or software technical support through chat (teams), email, and phone\r\n- Controlled remote devices by Teamviewer\r\n- Reset accounts and offered assistance to application users across France\r\n- Handled Windows 7/10, Active Directory, and managed the IT device fleet with 2 colleagues at level 2 and a level 3 supervisor\r\n- Created profiles and managed admin rights through IAM and Active Directory\r\n- Operated Azure portal and VPN pulse secure, with SmartIT as the work tool",
            "client_references": []
        },
        {
            "job_title": "1st Line of Expert Service",
            "company": "BOSCH",
            "duration": "10/2021 \u2013 03/2021",
            "description": "- Provided automotive technical service support for Bosch workshops\r\n- Diagnosed faults and errors for service technicians\r\n- Offered after-sales diagnostic software services\r\n- Utilized DDM and ESI Tronic for diagnostics, CDB for ticket management, Genesys for calls, and MS Office for other channels",
            "client_references": []
        },
        {
            "job_title": "B2B Support",
            "company": "FUJITSU",
            "duration": "07/2018 \u2013 03/2020",
            "description": "- Assisted users remotely\r\n- Offered technical support through chat, email, and phone with Bomgar remote control\r\n- Supported Office 365, IAM, Lotus Notes, Adobe, TeamCenter, Ariane, Sharepoint, and Windows 7/10\r\n- Handled escalations to Level 3\r\n- Managed profile creation and admin rights assignments via IAM and Active Directory\r\n- Operated VPN pulse secure, Citrix virtual machines, and ServiceNow tool\r\n- Supported Microsoft Azure console at level 2\r\n- Created Skype profiles, assisted level 1\r\n- Restored Sharepoint and shared files, updated knowledge base, reactivated connected printers, and managed level 2 telephone lines",
            "client_references": []
        },
        {
            "job_title": "B2B Support",
            "company": "SITEL",
            "duration": "12/2016 \u2013 06/2018",
            "description": "- Provided remote user assistance\r\n- Technical support through chat, email, and Bomgar remote control\r\n- Supported Office 365, Adobe, TeamCenter, Ariane, Sharepoint, Windows 7/10, Active Directory\r\n- Promoted to Level 2\r\n- Responsible for profile creation and admin rights assignment. Used Azure portal\r\n- Utilized VPN pulse secure, ServiceNow, and Citrix virtual machines",
            "client_references": []
        }
    ],
    "education": [],
    "certifications": [],
    "manager_name": "Reda QORCHI",
    "manager_email": "reda.qorchi@randstaddigital.lu",
    "manager_tel": "",
    "manager_role": "Delivery Manager"
}